tmodbus/__init__.py
tmodbus/_version.py
tmodbus/const.py
tmodbus/exceptions.py
tmodbus/py.typed
tmodbus/client/__init__.py
tmodbus/client/async_client.py
tmodbus/pdu/__init__.py
tmodbus/pdu/base.py
tmodbus/pdu/coils.py
tmodbus/pdu/device.py
tmodbus/pdu/discrete_inputs.py
tmodbus/pdu/exception_status.py
tmodbus/pdu/fifo.py
tmodbus/pdu/file.py
tmodbus/pdu/holding_registers.py
tmodbus/pdu/holding_registers_struct.py
tmodbus/pdu/serial_line.py
tmodbus/transport/__init__.py
tmodbus/transport/async_ascii.py
tmodbus/transport/async_base.py
tmodbus/transport/async_rtu.py
tmodbus/transport/async_rtu_over_tcp.py
tmodbus/transport/async_smart.py
tmodbus/transport/async_tcp.py
tmodbus/utils/__init__.py
tmodbus/utils/crc.py
tmodbus/utils/lrc.py
tmodbus/utils/raw_traffic_logger.py
tmodbus/utils/word_aware_struct.py
tmodbus-0.2.3.dist-info/METADATA
tmodbus-0.2.3.dist-info/WHEEL
tmodbus-0.2.3.dist-info/licenses/LICENSE
tmodbus-0.2.3.dist-info/RECORD
