Metadata-Version: 2.4
Name: tmodbus
Version: 0.2.3
Summary: A modern, strongly typed Modbus client library.
Project-URL: HomePage, https://github.com/wlcrs/tmodbus
Project-URL: Documentation, https://tmodbus.readthedocs.org
Project-URL: Repository, https://github.com/wlcrs/tmodbus
Project-URL: Issues, https://github.com/wlcrs/tmodbus/issues
Project-URL: Changelog, https://github.com/wlcrs/tmodbus/releases
Author: wlcrs
License: BSD-3-Clause
License-File: LICENSE
Keywords: modbus,modbus-ascii,modbus-rtu,modbus-rtu-over-tcp,modbus-tcp
Classifier: Development Status :: 4 - Beta
Classifier: Framework :: AsyncIO
Classifier: Intended Audience :: Developers
Classifier: License :: OSI Approved :: BSD License
Classifier: Programming Language :: Python :: 3.12
Classifier: Programming Language :: Python :: 3.13
Classifier: Programming Language :: Python :: 3.14
Classifier: Topic :: System :: Networking
Classifier: Typing :: Typed
Requires-Python: >=3.12
Requires-Dist: tenacity>=9.1.2
Provides-Extra: async-serial
Requires-Dist: pyserial-asyncio-fast>=0.16; extra == 'async-serial'
